pysamples/__init__.py
pysamples/pyenv/__init__.py
pysamples/pyorm/__init__.py
pysamples/pyorm/dbs/__init__.py
pysamples/pyorm/dbs/mysql.py
pysamples/pyorm/models/__init__.py
pysamples/pyorm/models/user.py
pysamples/pyunittest/__init__.py
pysamples/pyunittest/demo.py
pysamples/pyunittest/pyunittest.py
pysamples/pyunittest/test_demo_class.py
pysamples/pyunittest/test_demo_module.py
pysamples-0.0.4.dist-info/LICENSE
pysamples-0.0.4.dist-info/METADATA
pysamples-0.0.4.dist-info/WHEEL
pysamples-0.0.4.dist-info/top_level.txt
pysamples-0.0.4.dist-info/RECORD
