Metadata-Version: 2.1
Name: pysamples
Version: 0.0.4
Summary: Python samples package
Home-page: https://github.com/mdjdot/pysamples
Author: Dejian Meng
Author-email: medean@live.cn
License: MIT
Platform: UNKNOWN
Classifier: Programming Language :: Python :: 3
Classifier: License :: OSI Approved :: MIT License
Classifier: Operating System :: OS Independent
Requires-Python: >=3.7
